{
  "description": "RIA-7750 party ID generation when appeal is out of country with sponsor for start appeal",
  "request": {
    "uri": "/asylum/ccdAboutToSubmit",
    "credentials": "LegalRepresentative",
    "input": {
      "eventId": "startAppeal",
      "state": "appealStarted",
      "caseData": {
        "template": "minimal-appeal-started.json",
        "replacements": {
          "appellantInUk": "No",
          "hasSponsor": "Yes",
          "sponsorGivenNames": "test",
          "sponsorFamilyName": "some-name",
          "appellantPartyId": "randomAppellantPartyId",
          "legalRepIndividualPartyId": "randomLegalRepIndividualPartyId",
          "legalRepOrganisationPartyId": "randomLegalRepOrganisationPartyId",
          "sponsorPartyId": "randomSponsorPartyId"
        }
      }
    }
  },
  "expectation": {
    "status": 200,
    "errors": [],
    "caseData": {
      "template": "minimal-appeal-started.json",
      "replacements": {
        "appellantInUk": "No",
        "hasSponsor": "Yes",
        "appellantPartyId": "randomAppellantPartyId",
        "legalRepIndividualPartyId": "randomLegalRepIndividualPartyId",
        "legalRepOrganisationPartyId": "randomLegalRepOrganisationPartyId",
        "sponsorPartyId": "randomSponsorPartyId"
      }
    }
  }
}
